[
{
    "active": 3,
    "block": "2",
    "chainable": true,
    "hit": "4",
    "input": "5LP",
    "isNormal": true,
    "name": "Standing Light Punch",
    "recovery": 9,
    "startup": 7,
    "total": 18
},
{
    "active": 3,
    "block": "2",
    "chainable": true,
    "hit": "4",
    "input": "5LP",
    "isNormal": true,
    "name": "(Rapid cancel version)Standing Light Punch",
    "recovery": 9,
    "startup": 4,
    "total": 15
},
{
    "active": 2,
    "block": "-4",
    "chainable": false,
    "hit": "-2",
    "input": "5LK",
    "isNormal": true,
    "name": "Standing Light Kick",
    "recovery": 17,
    "startup": 7,
    "total": 25
},
{
    "active": 4,
    "block": "-2",
    "chainable": false,
    "hit": "2",
    "input": "5MP",
    "isNormal": true,
    "name": "Standing Medium Punch",
    "recovery": 17,
    "startup": 9,
    "total": 29
},
{
    "active": 4,
    "block": "-4",
    "chainable": false,
    "hit": "1",
    "input": "5MK",
    "isNormal": true,
    "name": "Standing Medium Kick",
    "recovery": 19,
    "startup": 10,
    "total": 32
},
{
    "active": 4,
    "block": "1",
    "chainable": false,
    "hit": "3",
    "input": "5HK",
    "isNormal": true,
    "name": "Standing Heavy Kick",
    "recovery": 21,
    "startup": 13,
    "total": 37
},
{
    "active": 2,
    "block": "1",
    "chainable": true,
    "hit": "6",
    "input": "2LP",
    "isNormal": true,
    "name": "Crouching Light Punch",
    "recovery": 8,
    "startup": 6,
    "total": 15
},
{
    "active": 2,
    "block": "1",
    "chainable": true,
    "hit": "6",
    "input": "2LP",
    "isNormal": true,
    "name": "(Rapid cancel version)Crouching Light Punch",
    "recovery": 8,
    "startup": 3,
    "total": 12
},
{
    "active": 3,
    "block": "-3",
    "chainable": true,
    "hit": "0",
    "input": "2LK",
    "isNormal": true,
    "name": "Crouching Light Kick",
    "recovery": 12,
    "startup": 4,
    "total": 18
},
{
    "active": 3,
    "block": "-3",
    "chainable": true,
    "hit": "0",
    "input": "2LK",
    "isNormal": true,
    "name": "(Rapid cancel version)Crouching Light Kick",
    "recovery": 12,
    "startup": 3,
    "total": 17
},
{
    "active": 3,
    "block": "-1",
    "chainable": false,
    "hit": "3",
    "input": "2MP",
    "isNormal": true,
    "name": "Crouching Medium Punch",
    "recovery": 16,
    "startup": 8,
    "total": 26
},
{
    "active": 3,
    "block": "-2",
    "chainable": false,
    "hit": "3",
    "input": "2MK",
    "isNormal": true,
    "name": "Crouching Medium Kick",
    "recovery": 18,
    "startup": 9,
    "total": 29
},
{
    "active": 9,
    "block": "-20",
    "chainable": false,
    "hit": "D",
    "input": "2HP",
    "isNormal": true,
    "name": "Crouching Heavy Punch",
    "recovery": 35,
    "startup": 11,
    "total": 54
},
{
    "active": 3,
    "block": "-13",
    "chainable": false,
    "hit": "D",
    "input": "2HK",
    "isNormal": true,
    "name": "Crouching Heavy Kick",
    "recovery": 27,
    "startup": 12,
    "total": 41
},
{
    "active": 3,
    "block": "-3",
    "chainable": false,
    "hit": "-1",
    "input": "3MP",
    "isNormal": true,
    "name": "Hellstab",
    "recovery": 21,
    "startup": 7,
    "total": 30
},
{
    "active": 7,
    "block": "-3",
    "chainable": false,
    "hit": "1",
    "input": "6MK",
    "isNormal": true,
    "name": "Knee Hammer",
    "recovery": 13,
    "startup": 14,
    "total": 33
},
{
    "active": 7,
    "block": "-9",
    "chainable": false,
    "hit": "D",
    "input": "6HK",
    "isNormal": true,
    "name": "Cyclone Wheel Kick",
    "recovery": 25,
    "startup": 22,
    "total": 53
},
{
    "active": 4,
    "block": "-18",
    "chainable": false,
    "hit": "D",
    "input": "3HK",
    "isNormal": true,
    "name": "Smetana Dropkick",
    "recovery": 40,
    "startup": 16,
    "total": 59
},
{
    "active": 3,
    "block": "-3",
    "chainable": false,
    "hit": "4",
    "input": "22MK",
    "isNormal": false,
    "name": "Power Stomps(1)",
    "recovery": 17,
    "startup": 9,
    "total": 28
},
{
    "active": 31,
    "block": "-12",
    "chainable": false,
    "hit": "D",
    "input": "5PP",
    "isNormal": true,
    "name": "Double Lariat",
    "recovery": 27,
    "startup": 15,
    "total": 72
},
{
    "active": 25,
    "block": "-11",
    "chainable": false,
    "hit": "D",
    "input": "LPMPHP",
    "isNormal": false,
    "name": "OD Double Lariat",
    "recovery": 26,
    "startup": 12,
    "total": 62
},
{
    "active": 3,
    "block": "",
    "chainable": false,
    "hit": "D",
    "input": "5LP",
    "isNormal": true,
    "name": "L Screw Piledriver",
    "recovery": 54,
    "startup": 5,
    "total": 61
},
{
    "active": 3,
    "block": "",
    "chainable": false,
    "hit": "D",
    "input": "5MP",
    "isNormal": true,
    "name": "M Screw Piledriver",
    "recovery": 54,
    "startup": 5,
    "total": 61
},
{
    "active": 3,
    "block": "",
    "chainable": false,
    "hit": "D",
    "input": "5HP",
    "isNormal": true,
    "name": "H Screw Piledriver",
    "recovery": 54,
    "startup": 5,
    "total": 61
},
{
    "active": 3,
    "block": "",
    "chainable": false,
    "hit": "D",
    "input": "5PP",
    "isNormal": true,
    "name": "OD Screw Piledriver",
    "recovery": 54,
    "startup": 5,
    "total": 61
},
{
    "active": 2,
    "block": "",
    "chainable": false,
    "hit": "D",
    "input": "63214K",
    "isNormal": false,
    "name": "Russian Suplex",
    "recovery": 50,
    "startup": 10,
    "total": 61
},
{
    "active": 2,
    "block": "",
    "chainable": false,
    "hit": "D",
    "input": "63214KK",
    "isNormal": false,
    "name": "OD Russian Suplex",
    "recovery": 50,
    "startup": 10,
    "total": 61
},
{
    "active": 2,
    "block": "",
    "chainable": false,
    "hit": "D",
    "input": "63214K",
    "isNormal": false,
    "name": "Siberian Express(Close range)",
    "recovery": 41,
    "startup": 28,
    "total": 70
},
{
    "active": 2,
    "block": "",
    "chainable": false,
    "hit": "D",
    "input": "63214KK",
    "isNormal": false,
    "name": "OD Siberian Express(Close range)",
    "recovery": 44,
    "startup": 23,
    "total": 68
},
{
    "active": 2,
    "block": "",
    "chainable": false,
    "hit": "D",
    "input": "63214K",
    "isNormal": false,
    "name": "Siberian Express(Far range)",
    "recovery": 40,
    "startup": 55,
    "total": 96
},
{
    "active": 2,
    "block": "",
    "chainable": false,
    "hit": "D",
    "input": "63214KK",
    "isNormal": false,
    "name": "OD Siberian Express(Far range)",
    "recovery": 40,
    "startup": 54,
    "total": 95
},
{
    "active": 51,
    "block": "",
    "chainable": false,
    "hit": "D",
    "input": "22HK",
    "isNormal": false,
    "name": "Tundra Storm",
    "recovery": 24,
    "startup": 5,
    "total": 79
},
{
    "active": 7,
    "block": "",
    "chainable": false,
    "hit": "D",
    "input": "236236K",
    "isNormal": false,
    "name": "SA1 Aerial Russian Slam",
    "recovery": 60,
    "startup": 11,
    "total": 77
},
{
    "active": 3,
    "block": "",
    "chainable": false,
    "hit": "",
    "input": "LPLK",
    "isNormal": false,
    "name": "Bodyslam",
    "recovery": 23,
    "startup": 5,
    "total": 30
},
{
    "active": 3,
    "block": "",
    "chainable": false,
    "hit": "",
    "input": "4LPLK",
    "isNormal": false,
    "name": "Capture Suplex",
    "recovery": 23,
    "startup": 5,
    "total": 30
},
{
    "active": 3,
    "block": "",
    "chainable": false,
    "hit": "",
    "input": "6LPLK",
    "isNormal": false,
    "name": "German Suplex",
    "recovery": 23,
    "startup": 5,
    "total": 30
},
{
    "active": 3,
    "block": "",
    "chainable": false,
    "hit": "",
    "input": "3LPLK",
    "isNormal": false,
    "name": "Spinebuster",
    "recovery": 23,
    "startup": 5,
    "total": 30
},
{
    "active": 3,
    "block": "",
    "chainable": false,
    "hit": "",
    "input": "1LPLK",
    "isNormal": false,
    "name": "Russian Drop",
    "recovery": 23,
    "startup": 5,
    "total": 30
},
{
    "active": 3,
    "block": "",
    "chainable": false,
    "hit": "",
    "input": "2LPLK",
    "isNormal": false,
    "name": "Brain Buster",
    "recovery": 23,
    "startup": 5,
    "total": 30
},
{
    "active": 0,
    "block": 0,
    "chainable": false,
    "hit": 0,
    "input": "66",
    "isNormal": false,
    "name": "Forward Dash",
    "recovery": 0,
    "startup": 0,
    "total": "22"
},
{
    "active": 2,
    "block": "-3",
    "chainable": false,
    "hit": "D",
    "input": "HPHK",
    "isNormal": false,
    "name": "Drive Impact: Double Russian Chop",
    "recovery": 35,
    "startup": 26,
    "total": 62
}]